swcpy_sdk/__init__.py
swcpy_sdk/swc_client.py
swcpy_sdk/swc_config.py
swcpy_sdk/schemas/__init__.py
swcpy_sdk/schemas/schemas.py
swcpy_sdk-0.0.1.dist-info/METADATA
swcpy_sdk-0.0.1.dist-info/WHEEL
swcpy_sdk-0.0.1.dist-info/top_level.txt
swcpy_sdk-0.0.1.dist-info/RECORD
