Metadata-Version: 2.4
Name: swcpy_sdk
Version: 0.0.1
Summary: Software Development Kit (SDK) for SWC API
Author: [Josue Aouda]
Classifier: Development Status :: 3 - Alpha
Classifier: Programming Language :: Python :: 3
Classifier: License :: OSI Approved :: MIT License
Classifier: Operating System :: OS Independent
Requires-Python: >=3.10
Requires-Dist: pytest>=8.1
Requires-Dist: httpx>=0.27.0
Requires-Dist: pydantic>=2.4.0
Requires-Dist: backoff>=2.2.1
Requires-Dist: pyarrow>=16.0
Requires-Dist: python-dotenv
